data_transformation_library_ingri/__init__.py
data_transformation_library_ingri/functions.py
data_transformation_library_ingri/validate.py
data_transformation_library_ingri-0.1.2.dist-info/METADATA
data_transformation_library_ingri-0.1.2.dist-info/WHEEL
data_transformation_library_ingri-0.1.2.dist-info/RECORD
