Metadata-Version: 2.1
Name: data-transformation-library-ingri
Version: 0.1.2
Summary: The Data Transformation Library is a Python package designed to provide a set of functions for common data transformation tasks, such as transposing matrices, performing convolutions.
Author: Ingrida
Author-email: ingrida.vilkancaite@gmail.com
Requires-Python: >=3.12,<4.0
Classifier: Programming Language :: Python :: 3
Classifier: Programming Language :: Python :: 3.12
Requires-Dist: numpy (>=1.26.4,<2.0.0)
Requires-Dist: requests (>=2.31.0,<3.0.0)
